geoLid/__init__.py
geoLid/geoLid.py
geoLid-1.0.dist-info/LICENSE
geoLid-1.0.dist-info/METADATA
geoLid-1.0.dist-info/WHEEL
geoLid-1.0.dist-info/top_level.txt
geoLid-1.0.dist-info/RECORD
