Metadata-Version: 2.1
Name: geoLid
Version: 1.0
Summary: Geographically-informed language identification
Home-page: https://github.com/jonathandunn/geoLid
Author: Jonathan Dunn
Author-email: jedunn@illinois.edu
License: GNU GENERAL PUBLIC LICENSE v3
Keywords: lid,language identification,geographic,geography
License-File: LICENSE
Requires-Dist: clean-text
Requires-Dist: fasttext
